MANIFEST.in
setup.py
TrebuchetRicochet.egg-info/PKG-INFO
TrebuchetRicochet.egg-info/SOURCES.txt
TrebuchetRicochet.egg-info/dependency_links.txt
TrebuchetRicochet.egg-info/entry_points.txt
TrebuchetRicochet.egg-info/requires.txt
TrebuchetRicochet.egg-info/top_level.txt
ricochet/__init__.py
ricochet/models.py
ricochet/routes.py
ricochet/auth/__init__.py
ricochet/auth/openid.py