Metadata-Version: 1.0
Name: TrebuchetRicochet
Version: 0.2
Summary: A web interface to trebuchet.
Home-page: https://github.com/trebuchet-deploy/ricochet
Author: Ryan Lane
Author-email: ryan@ryandlane.com
License: apache2
Platform: UNKNOWN
